finn/custom_hls/__init__.py
finn/custom_hls/checksum.cpp
finn/custom_hls/checksum.hpp
finn/custom_hls/checksum_tb.sv
finn/custom_hls/instrumentation.template.cpp
finn/custom_hls/instrumentation_sim.template.tcl
finn/custom_hls/instrumentation_tb.template.sv
finn/custom_hls/lookup.hpp
finn/custom_hls/virtual_fifo.hpp
finn/finn-rtllib/__init__.py
finn/finn-rtllib/axi/hdl/axilite.sv
finn/finn-rtllib/axi/sim/axilite_tb.sv
finn/finn-rtllib/axi_info/component.xml
finn/finn-rtllib/axi_info/hdl/axi_info.sv
finn/finn-rtllib/axi_info/hdl/axi_info_top.sv
finn/finn-rtllib/axi_info/xgui/axi_info_top_v1_0.tcl
finn/finn-rtllib/dwc/hdl/dwc.sv
finn/finn-rtllib/dwc/hdl/dwc_axi.sv
finn/finn-rtllib/dwc/hdl/dwc_template.v
finn/finn-rtllib/dwc/sim/dwc_axi_tb.sv
finn/finn-rtllib/dynload/hdl/dynamic_load.sv
finn/finn-rtllib/dynload/hdl/dynamic_load_wrapper_template.v
finn/finn-rtllib/dynload/hdl/ram_p_c.sv
finn/finn-rtllib/fifo/hdl/Q_srl.v
finn/finn-rtllib/fifo/hdl/fifo_gauge.sv
finn/finn-rtllib/fifo/hdl/fifo_gauge_tb.sv
finn/finn-rtllib/fifo/hdl/fifo_template.v
finn/finn-rtllib/fmpadding/hdl/axi2we.sv
finn/finn-rtllib/fmpadding/hdl/fmpadding.sv
finn/finn-rtllib/fmpadding/hdl/fmpadding_axi.sv
finn/finn-rtllib/fmpadding/hdl/fmpadding_axi_tb.sv
finn/finn-rtllib/fmpadding/hdl/fmpadding_template.v
finn/finn-rtllib/memstream/doc/README
finn/finn-rtllib/memstream/hdl/memstream.sv
finn/finn-rtllib/memstream/hdl/memstream_axi.sv
finn/finn-rtllib/memstream/hdl/memstream_wrapper_template.v
finn/finn-rtllib/memstream/sim/memstream_axi_tb.sv
finn/finn-rtllib/memstream/sim/memstream_tb.sv
finn/finn-rtllib/mvu/add_multi.sv
finn/finn-rtllib/mvu/mvu.sv
finn/finn-rtllib/mvu/mvu_pkg.sv
finn/finn-rtllib/mvu/mvu_vvu_8sx9_dsp58.sv
finn/finn-rtllib/mvu/mvu_vvu_axi.sv
finn/finn-rtllib/mvu/mvu_vvu_axi_wrapper.v
finn/finn-rtllib/mvu/replay_buffer.sv
finn/finn-rtllib/mvu/tb/add_multi_tb.sv
finn/finn-rtllib/mvu/tb/mvu_axi_tb.sv
finn/finn-rtllib/mvu/tb/replay_buffer_tb.sv
finn/finn-rtllib/mvu/tb/vvu_axi_tb.sv
finn_plus-1.2.0.dist-info/METADATA
finn_plus-1.2.0.dist-info/WHEEL
finn_plus-1.2.0.dist-info/entry_points.txt
finn_plus-1.2.0.dist-info/licenses/AUTHORS.rst
finn_plus-1.2.0.dist-info/licenses/LICENSE.txt
finn_plus-1.2.0.dist-info/RECORD
