Metadata-Version: 2.4
Name: finn-plus
Version: 1.2.0
Summary: Fork of FINN, a QNN dataflow compiler for AMD/Xilinx FPGAs
License-File: AUTHORS.rst
License-File: LICENSE.txt
Maintainer: Felix Jentzsch
Maintainer-email: felix.jentzsch@upb.de
Requires-Python: >=3.10,<3.12
Classifier: Programming Language :: Python :: 3
Classifier: Programming Language :: Python :: 3.10
Classifier: Programming Language :: Python :: 3.11
Requires-Dist: bitstring (>=4.3.1,<4.4.0)
Requires-Dist: click (>=8.1.8,<9.0.0)
Requires-Dist: clize (>=5.0.2,<5.1.0)
Requires-Dist: cmake (>=4.0.3,<4.1.0)
Requires-Dist: deap (>=1.4.3,<1.5.0)
Requires-Dist: dependencies (==2.0.1)
Requires-Dist: dvc[webdav] (>=3.59.1,<3.60.0)
Requires-Dist: dvclive[image] (>=3.48.2,<3.49.0)
Requires-Dist: gspread (>=3.6.0,<3.7.0)
Requires-Dist: importlib-resources (>=6.5.2,<6.6.0)
Requires-Dist: ipykernel (>=6.29.5,<6.30.0)
Requires-Dist: ipython (>=8.37.0,<8.38.0)
Requires-Dist: jupyter (>=1.1.1,<1.2.0)
Requires-Dist: markupsafe (>=3.0.2,<3.1.0)
Requires-Dist: mashumaro[yaml] (>=3.15,<4.0)
Requires-Dist: matplotlib (>=3.10.3,<3.11.0)
Requires-Dist: mip (>=1.13.0,<1.14.0)
Requires-Dist: netron (>5.0.0,<=8.5.0)
Requires-Dist: networkx (>=3.4.2,<3.5.0)
Requires-Dist: numpy (==1.26.4)
Requires-Dist: onnx (==1.17.0)
Requires-Dist: onnxoptimizer (>=0.3.13,<0.4.0)
Requires-Dist: onnxruntime (==1.20.1)
Requires-Dist: pandas (>=2.3.1,<2.4.0)
Requires-Dist: pre-commit (>=4.2.0,<4.3.0)
Requires-Dist: protobuf (==3.20.3)
Requires-Dist: psutil (>=5.9.4,<5.10.0)
Requires-Dist: pygments (>=2.19.2,<2.20.0)
Requires-Dist: pyscaffold (>=4.6,<4.7)
Requires-Dist: pytest (>=8.4.1,<8.5.0)
Requires-Dist: pytest-cov (>=6.2.1,<6.3.0)
Requires-Dist: pytest-dependency (>=0.6.0,<0.7.0)
Requires-Dist: pytest-forked (>=1.6.0,<1.7.0)
Requires-Dist: pytest-html (>=4.1.1,<4.2.0)
Requires-Dist: pytest-html-merger (>=0.1.0,<0.2.0)
Requires-Dist: pytest-metadata (>=3.1.1,<3.2.0)
Requires-Dist: pytest-parallel (>=0.1.1,<0.2.0)
Requires-Dist: pytest-rerunfailures (>=15.1,<15.2)
Requires-Dist: pytest-xdist[setproctitle] (>=3.6.1,<3.7.0)
Requires-Dist: pyyaml (>=6.0.2,<6.1.0)
Requires-Dist: rich (>=13.9.4,<14.0.0)
Requires-Dist: scikit-learn (>=1.7.0,<1.8.0)
Requires-Dist: scipy (>=1.15.0,<1.16.0)
Requires-Dist: setupext-janitor (>=1.1.2,<2.0.0)
Requires-Dist: setuptools (>40.8.0,<70.0.0)
Requires-Dist: sigtools (>=4.0.1,<4.1.0)
Requires-Dist: tclwrapper (==0.0.1)
Requires-Dist: termcolor (>=2.5.0,<3.0.0)
Requires-Dist: tokenize-rt (>=4.2.1,<4.3.0)
Requires-Dist: toposort (>=1.7.0,<1.8.0)
Requires-Dist: torch (>=2.7.1,<2.8.0)
Requires-Dist: torchvision (>=0.22.1,<0.23.0)
Requires-Dist: tqdm (>=4.67.1,<4.68.0)
Requires-Dist: vcdvcd (>=1.0.5,<1.1.0)
Requires-Dist: wget (>=3.2,<3.3)
Project-URL: EKI Project, https://www.eki-project.tech/
Project-URL: GitHub, https://github.com/eki-project/finn-plus
